pyenv_enc/__init__.py
pyenv_enc/enc.py
pyenv_encrypt-0.1.2.dist-info/LICENSE
pyenv_encrypt-0.1.2.dist-info/METADATA
pyenv_encrypt-0.1.2.dist-info/WHEEL
pyenv_encrypt-0.1.2.dist-info/entry_points.txt
pyenv_encrypt-0.1.2.dist-info/top_level.txt
pyenv_encrypt-0.1.2.dist-info/RECORD
