Metadata-Version: 2.1
Name: pyenv-encrypt
Version: 0.1.2
Summary: GPG based env file encryptor utility.
Author-email: Akhlak Mahmood <akhlakm@gatech.edu>
Project-URL: Homepage, https://github.com/akhlakm/pyenv-encrypt
Project-URL: Bug Tracker, https://github.com/akhlakm/pyenv-encrypt/issues
Keywords: encryption,development
Classifier: Operating System :: OS Independent
Classifier: Programming Language :: Python :: 3
Classifier: License :: OSI Approved :: MIT License
Requires-Python: >=3.0
License-File: LICENSE
Requires-Dist: pyyaml
Requires-Dist: python-dotenv
